normality/__init__.py
normality/cleaning.py
normality/constants.py
normality/encoding.py
normality/paths.py
normality/py.typed
normality/scripts.py
normality/slugify.py
normality/stringify.py
normality/transliteration.py
normality/util.py
normality-3.0.1.dist-info/METADATA
normality-3.0.1.dist-info/WHEEL
normality-3.0.1.dist-info/licenses/LICENSE
normality-3.0.1.dist-info/RECORD
