Metadata-Version: 2.4
Name: normality
Version: 3.0.1
Summary: Micro-library to normalize text strings
Project-URL: Documentation, https://github.com/pudo/normality
Project-URL: Repository, https://github.com/pudo/normality.git
Project-URL: Issues, https://github.com/pudo/normality/issues
Author-email: Friedrich Lindenberg <friedrich@pudo.org>
License: Copyright (c) 2013-2025, Friedrich Lindenberg, Gregor Aisch
License-File: LICENSE
Keywords: normalization,slugs,text,unicode
Classifier: Development Status :: 3 - Alpha
Classifier: Intended Audience :: Developers
Classifier: License :: OSI Approved :: MIT License
Classifier: Operating System :: OS Independent
Classifier: Programming Language :: Python :: 3.9
Classifier: Programming Language :: Python :: 3.10
Classifier: Programming Language :: Python :: 3.11
Classifier: Programming Language :: Python :: 3.12
Requires-Python: >=3.9
Requires-Dist: banal>=1.0.1
Requires-Dist: chardet
Requires-Dist: charset-normalizer>=2.0.0
Requires-Dist: pyicu>=2.10.0
Provides-Extra: dev
Requires-Dist: build; extra == 'dev'
Requires-Dist: mypy; extra == 'dev'
Requires-Dist: pytest; extra == 'dev'
Requires-Dist: types-chardet; extra == 'dev'
Requires-Dist: wheel; extra == 'dev'
Provides-Extra: icu
